pandalchemize/__init__.py
pandalchemize/records.py
pandalchemize/sqldataframe.py
pandalchemize/sqltable.py
pandalchemize-0.1.1.dist-info/LICENSE
pandalchemize-0.1.1.dist-info/METADATA
pandalchemize-0.1.1.dist-info/WHEEL
pandalchemize-0.1.1.dist-info/top_level.txt
pandalchemize-0.1.1.dist-info/RECORD
